example_package/__init__.py
example_package/hello.py
example_package-0.0.1.dist-info/LICENSE
example_package-0.0.1.dist-info/METADATA
example_package-0.0.1.dist-info/WHEEL
example_package-0.0.1.dist-info/top_level.txt
example_package-0.0.1.dist-info/RECORD
