Metadata-Version: 2.1
Name: example_package
Version: 0.0.1
Summary: A small example package
Home-page: https://github.com/gvickyviki1/m_frame
Author: Example Author
Author-email: vigneshkumar.g@prodapt.com
License: UNKNOWN
Platform: UNKNOWN
Classifier: Programming Language :: Python :: 3
Classifier: License :: OSI Approved :: MIT License
Classifier: Operating System :: OS Independent
